swarmlib/LICENSE.txt
swarmlib/ThirdPartyNotices.txt
swarmlib/__init__.py
swarmlib/__main__.py
swarmlib/_version.py
swarmlib/abc/__init__.py
swarmlib/abc/abc_problem.py
swarmlib/abc/main.py
swarmlib/abc/visualizer.py
swarmlib/abc/bees/__init__.py
swarmlib/abc/bees/bee_base.py
swarmlib/abc/bees/employee_bee.py
swarmlib/abc/bees/onlooker_bee.py
swarmlib/aco4tsp/__init__.py
swarmlib/aco4tsp/aco_problem.py
swarmlib/aco4tsp/ant.py
swarmlib/aco4tsp/local_2_opt.py
swarmlib/aco4tsp/main.py
swarmlib/aco4tsp/tsp_graph.py
swarmlib/aco4tsp/visualizer.py
swarmlib/aco4tsp/resources/burma14.tsp
swarmlib/cuckoosearch/__init__.py
swarmlib/cuckoosearch/cuckoo_problem.py
swarmlib/cuckoosearch/main.py
swarmlib/cuckoosearch/nest.py
swarmlib/cuckoosearch/visualizer.py
swarmlib/fireflyalgorithm/__init__.py
swarmlib/fireflyalgorithm/firefly.py
swarmlib/fireflyalgorithm/firefly_problem.py
swarmlib/fireflyalgorithm/main.py
swarmlib/gwo/__init__.py
swarmlib/gwo/gwo_problem.py
swarmlib/gwo/main.py
swarmlib/gwo/visualizer.py
swarmlib/gwo/wolf.py
swarmlib/pso/__init__.py
swarmlib/pso/main.py
swarmlib/pso/particle.py
swarmlib/pso/pso_problem.py
swarmlib/util/__init__.py
swarmlib/util/base_visualizer.py
swarmlib/util/coordinate.py
swarmlib/util/functions.py
swarmlib/util/levy_flight.py
swarmlib/util/problem_base.py
swarmlib/util/visualizer_base.py
swarmlib/woa/__init__.py
swarmlib/woa/main.py
swarmlib/woa/whale.py
swarmlib/woa/woa_problem.py
swarmlib-0.14.1.dist-info/LICENSE.txt
swarmlib-0.14.1.dist-info/METADATA
swarmlib-0.14.1.dist-info/WHEEL
swarmlib-0.14.1.dist-info/entry_points.txt
swarmlib-0.14.1.dist-info/top_level.txt
swarmlib-0.14.1.dist-info/RECORD
