Metadata-Version: 2.1
Name: swarmlib
Version: 0.14.1
Summary: Implementation and visualization of different swarm optimization algorithms.
Home-page: UNKNOWN
Author: Leo Hanisch
License: BSD 3-Clause License
Project-URL: Documentation, https://github.com/HaaLeo/swarmlib/wiki
Project-URL: Source, https://github.com/HaaLeo/swarmlib
Project-URL: Issue Tracker, https://github.com/HaaLeo/swarmlib/issues
Project-URL: Changelog, https://github.com/HaaLeo/swarmlib/blob/master/CHANGELOG.md#changelog
Project-URL: Funding, https://github.com/sponsors/HaaLeo
Project-URL: gitter.im, https://gitter.im/HaaLeo/swarmlib
Keywords: swarm,swarmlib,lib,library,ant,colony,optimization,optimisation,traveling,salesman,problem,TSP,tsp,ACO,aco,TSPLIB95,tsplib95networkx,visualization,matplotlib,firefly,fireflies,algorithm,cuckoo,cuckoos,search,levy,flights,particle,particles,pso,PSO,artificial,bee,bees,colony,ABC,abc,heuristic,grey,wolf,optimizer,gwo,GWO,whale,whales,WOA,woa
Platform: UNKNOWN
Classifier: Development Status :: 5 - Production/Stable
Classifier: Intended Audience :: Education
Classifier: Intended Audience :: Information Technology
Classifier: Intended Audience :: Science/Research
Classifier: Intended Audience :: Developers
Classifier: License :: OSI Approved :: BSD License
Classifier: Operating System :: OS Independent
Classifier: Programming Language :: Python :: 3
Classifier: Programming Language :: Python :: 3.6
Classifier: Programming Language :: Python :: 3.7
Classifier: Programming Language :: Python :: 3.8
Classifier: Programming Language :: Python :: 3.9
Classifier: Programming Language :: Python :: Implementation
Classifier: Programming Language :: Python :: Implementation :: PyPy
Classifier: Topic :: Education
Classifier: Topic :: Scientific/Engineering
Classifier: Topic :: Scientific/Engineering :: Artificial Intelligence
Classifier: Topic :: Scientific/Engineering :: Bio-Informatics
Classifier: Topic :: Scientific/Engineering :: Information Analysis
Classifier: Topic :: Scientific/Engineering :: Mathematics
Classifier: Topic :: Scientific/Engineering :: Visualization
Classifier: Topic :: Software Development :: Libraries
Classifier: Topic :: Software Development :: Libraries :: Python Modules
Classifier: Topic :: Utilities
Requires-Python: >=3.6
Requires-Dist: landscapes (==0.0.11)
Requires-Dist: tsplib95 (<1.0.0,>=0.7.1)
Requires-Dist: matplotlib (<4.0.0,>=3.3.2)
Requires-Dist: networkx (<3.0,>=2.5)
Requires-Dist: numpy (<2.0.0,>=1.19.3)
